{
  "resource": "Vutes",
  "http_method": "GET",
  "route": "/api/v1/vutes",
  "description": "List vutes",
  "explanation": null,
  "parameters": [

  ],
  "response_fields": [

  ],
  "requests": [
    {
      "request_method": "GET",
      "request_path": "/api/v1/vutes",
      "request_body": null,
      "request_headers": {
        "Content-Type": "application/vnd.api+json",
        "Authorization": "Bearer 27420d8f0647e9846837e9adcf9d9f86bc0e131e49d2f493331d5b9a47df7270"
      },
      "request_query_parameters": {
      },
      "request_content_type": "application/vnd.api+json",
      "response_status": 200,
      "response_status_text": "OK",
      "response_body": "{\"data\":[{\"id\":\"240\",\"type\":\"vutes\",\"links\":{\"self\":\"http://example.org/api/v1/vutes/240\"},\"attributes\":{\"created-at\":\"2015-10-27T02:10:10.432Z\",\"updated-at\":\"2015-10-27T02:10:10.432Z\",\"keyword\":\"Use the open-source RAM bandwidth, then you can input the optical monitor!\",\"user-id\":438},\"relationships\":{\"user\":{\"links\":{\"self\":\"http://example.org/api/v1/vutes/240/relationships/user\",\"related\":\"http://example.org/api/v1/vutes/240/user\"}}}},{\"id\":\"241\",\"type\":\"vutes\",\"links\":{\"self\":\"http://example.org/api/v1/vutes/241\"},\"attributes\":{\"created-at\":\"2015-10-27T02:10:10.436Z\",\"updated-at\":\"2015-10-27T02:10:10.436Z\",\"keyword\":\"I'll hack the optical USB interface, that should pixel the USB feed!\",\"user-id\":438},\"relationships\":{\"user\":{\"links\":{\"self\":\"http://example.org/api/v1/vutes/241/relationships/user\",\"related\":\"http://example.org/api/v1/vutes/241/user\"}}}}],\"meta\":{\"record-count\":2},\"links\":{\"first\":\"http://example.org/api/v1/vutes?page%5Blimit%5D=100\\u0026page%5Boffset%5D=0\",\"last\":\"http://example.org/api/v1/vutes?page%5Blimit%5D=100\\u0026page%5Boffset%5D=0\"}}",
      "response_headers": {
        "Content-Type": "application/vnd.api+json"
      },
      "response_content_type": "application/vnd.api+json",
      "curl": "curl \"http://localhost:3000/api/v1/vutes\" -X GET \\\n\t-H \"Content-Type: application/vnd.api+json\" \\\n\t-H \"Accept: application/vnd.api+json\" \\\n\t-H \"Authorization: Bearer 27420d8f0647e9846837e9adcf9d9f86bc0e131e49d2f493331d5b9a47df7270\""
    }
  ]
}